{
  "main": {
    "id": "6a169d746bd7a38c",
    "type": "split",
    "children": [
      {
        "id": "f3aee03b3d086d7f",
        "type": "tabs",
        "children": [
          {
            "id": "dfe39ad7fc5765fb",
            "type": "leaf",
            "state": {
              "type": "markdown",
              "state": {
                "file": "ProgrammingKnowledge/Programming/Concepts/Testing/Property Based Testing.md",
                "mode": "source",
                "source": false
              }
            }
          },
          {
            "id": "2dd3cacb124f3136",
            "type": "leaf",
            "state": {
              "type": "image",
              "state": {
                "file": "ProgrammingKnowledge/Programming/Git/Git history/Pasted image 20231129201720.png"
              }
            }
          },
          {
            "id": "37ebf039b931867c",
            "type": "leaf",
            "state": {
              "type": "markdown",
              "state": {
                "file": "ProgrammingKnowledge/Programming/Git/Git stash, keep index.md",
                "mode": "source",
                "source": false
              }
            }
          },
          {
            "id": "117d36aec49eccad",
            "type": "leaf",
            "state": {
              "type": "markdown",
              "state": {
                "file": "ProgrammingKnowledge/IT/Docker/DNS.md",
                "mode": "source",
                "source": false
              }
            }
          }
        ],
        "currentTab": 3
      }
    ],
    "direction": "vertical"
  },
  "left": {
    "id": "21822312f3631e22",
    "type": "split",
    "children": [
      {
        "id": "5631c5b02caa7c45",
        "type": "tabs",
        "children": [
          {
            "id": "8c52df5aa08da735",
            "type": "leaf",
            "state": {
              "type": "file-explorer",
              "state": {
                "sortOrder": "alphabetical"
              }
            }
          },
          {
            "id": "af14a800e820c0f9",
            "type": "leaf",
            "state": {
              "type": "search",
              "state": {
                "query": "",
                "matchingCase": false,
                "explainSearch": false,
                "collapseAll": false,
                "extraContext": false,
                "sortOrder": "alphabetical"
              }
            }
          },
          {
            "id": "17624902616b7647",
            "type": "leaf",
            "state": {
              "type": "starred",
              "state": {}
            }
          },
          {
            "id": "4dbb4e2eb2c49425",
            "type": "leaf",
            "state": {
              "type": "bookmarks",
              "state": {}
            }
          }
        ]
      }
    ],
    "direction": "horizontal",
    "width": 300
  },
  "right": {
    "id": "53950853587d6193",
    "type": "split",
    "children": [
      {
        "id": "a84ebb2c84fd7649",
        "type": "tabs",
        "children": [
          {
            "id": "e2a80269c3a8d106",
            "type": "leaf",
            "state": {
              "type": "backlink",
              "state": {
                "file": "ProgrammingKnowledge/IT/Docker/DNS.md",
                "collapseAll": false,
                "extraContext": false,
                "sortOrder": "alphabetical",
                "showSearch": false,
                "searchQuery": "",
                "backlinkCollapsed": false,
                "unlinkedCollapsed": true
              }
            }
          },
          {
            "id": "ada380909c406c81",
            "type": "leaf",
            "state": {
              "type": "outgoing-link",
              "state": {
                "file": "ProgrammingKnowledge/IT/Docker/DNS.md",
                "linksCollapsed": false,
                "unlinkedCollapsed": true
              }
            }
          },
          {
            "id": "36ac126edeb00386",
            "type": "leaf",
            "state": {
              "type": "tag",
              "state": {
                "sortOrder": "frequency",
                "useHierarchy": true
              }
            }
          },
          {
            "id": "ed88d3f20468a4b9",
            "type": "leaf",
            "state": {
              "type": "outline",
              "state": {
                "file": "ProgrammingKnowledge/IT/Docker/DNS.md"
              }
            }
          },
          {
            "id": "d6db890e57d41d34",
            "type": "leaf",
            "state": {
              "type": "calendar",
              "state": {}
            }
          }
        ],
        "currentTab": 4
      }
    ],
    "direction": "horizontal",
    "width": 300,
    "collapsed": true
  },
  "left-ribbon": {
    "hiddenItems": {
      "switcher:Open quick switcher": false,
      "graph:Open graph view": false,
      "canvas:Create new canvas": false,
      "daily-notes:Open today's daily note": false,
      "templates:Insert template": false,
      "command-palette:Open command palette": false
    }
  },
  "active": "117d36aec49eccad",
  "lastOpenFiles": [
    "ProgrammingKnowledge/IT/Docker/Networking.md",
    "ProgrammingKnowledge/IT/Docker/DNS.md",
    "ProgrammingKnowledge/Programming/Git/Git history/Git history.md",
    "ProgrammingKnowledge/IT/Docker",
    "ProgrammingKnowledge/Programming/Git/Reflog/Reflog.md",
    "ProgrammingKnowledge/Programming/Git/Git fundamentals/Git fundamentals.md",
    "ProgrammingKnowledge/Programming/Git/Git branching/Git branching.md",
    "ProgrammingKnowledge/Programming/Git/Git add partial parts of file.md",
    "ProgrammingKnowledge/Programming/Git/Git alias.md",
    "ProgrammingKnowledge/Programming/Git/Git commit.md",
    "ProgrammingKnowledge/Programming/Git/Git diff.md",
    "ProgrammingKnowledge/Programming/Git/Git show.md",
    "ProgrammingKnowledge/Programming/Git/Git stash, keep index.md",
    "ProgrammingKnowledge/Programming/Git/Git reset/Git reset.md",
    "Untitled.md",
    "ProgrammingKnowledge/Programming/Git/Git history/Pasted image 20231129202746.png",
    "ProgrammingKnowledge/Programming/Git/Git history/Pasted image 20231129204349.png",
    "Pasted image 20231129204320.png",
    "ProgrammingKnowledge/Programming/Git/Git history/Pasted image 20231129204631.png",
    "ProgrammingKnowledge/Programming/Git/Git history/Pasted image 20231129204238.png",
    "ProgrammingKnowledge/Programming/Git/Git history/Pasted image 20231129203638.png",
    "ProgrammingKnowledge/Programming/Git/Git history/Pasted image 20231129203505.png",
    "ProgrammingKnowledge/Programming/Git/Git history/Pasted image 20231129202847.png",
    "Pasted image 20231129202542.png",
    "ProgrammingKnowledge/Programming/Git/Git history/Pasted image 20231129202618.png",
    "ProgrammingKnowledge/Programming/Concepts/Testing/Property Based Testing.md",
    "ProgrammingKnowledge/Programming/Git/Git history",
    "ProgrammingKnowledge/Programming/Git/Git fundamentals",
    "ProgrammingKnowledge/Programming/Git/Git branching",
    "ProgrammingKnowledge/Programming/Git/Reflog",
    "ProgrammingKnowledge/Programming/Git/Git reset",
    "ProgrammingKnowledge/IT/Cloud/Azure/IOT Services/Azure IOT Services.md",
    "ProgrammingKnowledge/Programming/Git",
    "ProgrammingKnowledge/IT/Cloud/Azure/IOT Services/Azure Sphere.md",
    "ProgrammingKnowledge/IT/Cloud/Azure/IOT Services/Azure IOT Hub.md",
    "ProgrammingKnowledge/IT/Cloud/Azure/IOT Services/Azure IOT Central.md",
    "ProgrammingKnowledge/IT/Cloud/Azure/Azure.md",
    "ProgrammingKnowledge/IT/Cloud/Azure/Storage Services/Azure Storage Account.md",
    "ProgrammingKnowledge/IT/Windows/Activate Re.md",
    "ProgrammingKnowledge/IT/Windows/Remote Desktop/Activate Remote Desktop.md",
    "ProgrammingKnowledge/IT/Links/Limited.md",
    "ProgrammingKnowledge/IT/Databases/PostgreSql/Partitioning.md"
  ]
}