{
  "main": {
    "id": "45c17030b549c7ad",
    "type": "split",
    "children": [
      {
        "id": "247862708206086d",
        "type": "tabs",
        "children": [
          {
            "id": "719e491669cf69ca",
            "type": "leaf",
            "state": {
              "type": "markdown",
              "state": {
                "file": "Bewerbung_ENIO/Besprechung_14_10_2022.md",
                "mode": "source",
                "source": false
              }
            }
          },
          {
            "id": "0cdffde3d67da56d",
            "type": "leaf",
            "state": {
              "type": "markdown",
              "state": {
                "file": "Programming/CSharp/CSharp.md",
                "mode": "source",
                "source": false
              }
            }
          },
          {
            "id": "64fda3b9349fe581",
            "type": "leaf",
            "state": {
              "type": "markdown",
              "state": {
                "file": "Programming/Refactoring/What is Refactoring.md",
                "mode": "source",
                "source": false
              }
            }
          }
        ],
        "currentTab": 2
      }
    ],
    "direction": "vertical"
  },
  "left": {
    "id": "f57b16d45444261c",
    "type": "split",
    "children": [
      {
        "id": "be829fa37b1e34ff",
        "type": "tabs",
        "children": [
          {
            "id": "f681c5a6bb3f67c9",
            "type": "leaf",
            "state": {
              "type": "file-explorer",
              "state": {
                "sortOrder": "alphabetical"
              }
            }
          },
          {
            "id": "06e60e632021d933",
            "type": "leaf",
            "state": {
              "type": "search",
              "state": {
                "query": "Remote De",
                "matchingCase": false,
                "explainSearch": false,
                "collapseAll": false,
                "extraContext": false,
                "sortOrder": "alphabetical"
              }
            }
          }
        ]
      }
    ],
    "direction": "horizontal",
    "width": 432
  },
  "right": {
    "id": "9173b503a4d3970d",
    "type": "split",
    "children": [
      {
        "id": "40c144d23db91340",
        "type": "tabs",
        "children": [
          {
            "id": "d88d8d75be6c0f4b",
            "type": "leaf",
            "state": {
              "type": "backlink",
              "state": {
                "file": "Programming/Refactoring/What is Refactoring.md",
                "collapseAll": false,
                "extraContext": false,
                "sortOrder": "alphabetical",
                "showSearch": false,
                "searchQuery": "",
                "backlinkCollapsed": false,
                "unlinkedCollapsed": true
              }
            }
          },
          {
            "id": "9bcb864bb6df6b88",
            "type": "leaf",
            "state": {
              "type": "tag",
              "state": {
                "sortOrder": "frequency",
                "useHierarchy": true
              }
            }
          }
        ]
      }
    ],
    "direction": "horizontal",
    "width": 300
  },
  "ribbon": {
    "mostRecentAction": ""
  },
  "active": "64fda3b9349fe581",
  "lastOpenFiles": [
    "Programming/CSharp/CSharp.md",
    "Programming/CSharp/OpenSource/MediatR.md",
    "Programming/Web Developing/CSS/Collapsing Margins.md",
    "Programming/Web Developing/CSS/Viewport.md",
    "Programming/Web Developing/CSS/Canvas.md",
    "Programming/Design/Terminology/Devil's Advocate.md",
    "Programming/Design/Terminology/Walking skeleton.md",
    "Programming/CSharp/MSBuild/Runtime IDs.md",
    "Programming/CSharp/MSTest/MSTest Parameterized Tests.md",
    "Programming/CSharp/Website to know.md"
  ]
}