{
  "main": {
    "id": "45c17030b549c7ad",
    "type": "split",
    "children": [
      {
        "id": "247862708206086d",
        "type": "tabs",
        "children": [
          {
            "id": "64fda3b9349fe581",
            "type": "leaf",
            "state": {
              "type": "markdown",
              "state": {
                "file": "Programming/Languages/CSharp/Tools/LinqPad/LinqPad.md",
                "mode": "source",
                "source": false
              }
            }
          },
          {
            "id": "65c8863a8d9a2b9a",
            "type": "leaf",
            "state": {
              "type": "markdown",
              "state": {
                "file": "Programming/Languages/CSharp/Tools/LinqPad/Connect To Databases/Connect Linqpad to SQLLite.md",
                "mode": "source",
                "source": false
              }
            }
          },
          {
            "id": "90596888a97113bd",
            "type": "leaf",
            "state": {
              "type": "markdown",
              "state": {
                "file": "Programming/Languages/CSharp/Libraries/EFCore/Use SqlLite/SQLLite with EFCore.md",
                "mode": "source",
                "source": false
              }
            }
          },
          {
            "id": "8801276fdd510e0b",
            "type": "leaf",
            "state": {
              "type": "markdown",
              "state": {
                "file": "Programming/Languages/CSharp/Libraries/LanguageExt/LanguageExt.md",
                "mode": "source",
                "source": false
              }
            }
          },
          {
            "id": "7c4c573532925221",
            "type": "leaf",
            "state": {
              "type": "markdown",
              "state": {
                "file": "Programming/Languages/CSharp/Libraries/LanguageExt/LanguageExt.md",
                "mode": "source",
                "source": false
              }
            }
          },
          {
            "id": "642f0e1467a267dc",
            "type": "leaf",
            "state": {
              "type": "markdown",
              "state": {
                "file": "Programming/Languages/CSharp/Libraries/LanguageExt/Validation.md",
                "mode": "source",
                "source": false
              }
            }
          },
          {
            "id": "76262de926c7943f",
            "type": "leaf",
            "state": {
              "type": "markdown",
              "state": {
                "file": "Programming/Languages/Protobuf/Proto Files.md",
                "mode": "source",
                "source": false
              }
            }
          },
          {
            "id": "d74a6a8df83cd11e",
            "type": "leaf",
            "state": {
              "type": "markdown",
              "state": {
                "file": "IT/Security/OAuth 2.0.md",
                "mode": "source",
                "source": false
              }
            }
          },
          {
            "id": "dc4605e89429e7dd",
            "type": "leaf",
            "state": {
              "type": "image",
              "state": {
                "file": "IT/Security/Pasted image 20230307090806.png"
              }
            }
          },
          {
            "id": "defea67af33f5775",
            "type": "leaf",
            "state": {
              "type": "markdown",
              "state": {
                "file": "Programming/Languages/CSharp/CallerArgumentExpression.md",
                "mode": "source",
                "source": false
              }
            }
          },
          {
            "id": "95e503a62d424434",
            "type": "leaf",
            "state": {
              "type": "markdown",
              "state": {
                "file": "Programming/Concepts/Design/Event Sourcing.md",
                "mode": "source",
                "source": false
              }
            }
          },
          {
            "id": "01ac6d43e6843ee1",
            "type": "leaf",
            "state": {
              "type": "markdown",
              "state": {
                "file": "Programming/Languages/CSharp/UsefulExtension_Helpers_Patterns/Make Task canceable.md",
                "mode": "source",
                "source": false
              }
            }
          },
          {
            "id": "34dacd70af47b3de",
            "type": "leaf",
            "state": {
              "type": "graph",
              "state": {}
            }
          },
          {
            "id": "1fdef3c095faca08",
            "type": "leaf",
            "state": {
              "type": "empty",
              "state": {}
            }
          },
          {
            "id": "594cb25c7acd62ac",
            "type": "leaf",
            "state": {
              "type": "markdown",
              "state": {
                "file": "Programming/Languages/CSharp/Language/Task/TaskCompletationSource.md",
                "mode": "source",
                "source": false
              }
            }
          }
        ],
        "currentTab": 9
      }
    ],
    "direction": "vertical"
  },
  "left": {
    "id": "f57b16d45444261c",
    "type": "split",
    "children": [
      {
        "id": "be829fa37b1e34ff",
        "type": "tabs",
        "children": [
          {
            "id": "f681c5a6bb3f67c9",
            "type": "leaf",
            "state": {
              "type": "file-explorer",
              "state": {
                "sortOrder": "alphabetical"
              }
            }
          },
          {
            "id": "06e60e632021d933",
            "type": "leaf",
            "state": {
              "type": "search",
              "state": {
                "query": "validation",
                "matchingCase": false,
                "explainSearch": false,
                "collapseAll": false,
                "extraContext": false,
                "sortOrder": "alphabetical"
              }
            }
          }
        ]
      }
    ],
    "direction": "horizontal",
    "width": 439.5
  },
  "right": {
    "id": "9173b503a4d3970d",
    "type": "split",
    "children": [
      {
        "id": "40c144d23db91340",
        "type": "tabs",
        "children": [
          {
            "id": "d88d8d75be6c0f4b",
            "type": "leaf",
            "state": {
              "type": "backlink",
              "state": {
                "file": "Programming/Languages/CSharp/CallerArgumentExpression.md",
                "collapseAll": false,
                "extraContext": false,
                "sortOrder": "alphabetical",
                "showSearch": false,
                "searchQuery": "",
                "backlinkCollapsed": false,
                "unlinkedCollapsed": true
              }
            }
          },
          {
            "id": "9bcb864bb6df6b88",
            "type": "leaf",
            "state": {
              "type": "tag",
              "state": {
                "sortOrder": "frequency",
                "useHierarchy": true
              }
            }
          },
          {
            "id": "dd443d4fa96a8c5d",
            "type": "leaf",
            "state": {
              "type": "outline",
              "state": {
                "file": "Programming/Languages/CSharp/CallerArgumentExpression.md"
              }
            }
          }
        ]
      }
    ],
    "direction": "horizontal",
    "width": 200,
    "collapsed": true
  },
  "left-ribbon": {
    "hiddenItems": {
      "switcher:Open quick switcher": false,
      "graph:Open graph view": false,
      "canvas:Create new canvas": false,
      "command-palette:Open command palette": false,
      "markdown-importer:Open format converter": false,
      "templates:Insert template": false
    }
  },
  "active": "defea67af33f5775",
  "lastOpenFiles": [
    "IT/Security/Pasted image 20230307090806.png",
    "Programming/Languages/CSharp/CallerArgumentExpression.md",
    "IT/Security/Pasted image 20230307090354.png",
    "IT/Security/Pasted image 20230307084520.png",
    "IT/Security/Pasted image 20230307084422.png",
    "IT/Security/Pasted image 20230307084155.png",
    "IT/Security/Pasted image 20230306161211.png",
    "IT/Security/Pasted image 20230306161031.png",
    "IT/Security/Pasted image 20230306160556.png",
    "IT/Security/OpenID Connect.md",
    "IT/Security/OAuth 2.0.md",
    "Programming/Languages/Protobuf/Proto Files.md",
    "IT/Security",
    "Programming/Languages/CSharp/Libraries/LanguageExt/Validation.md",
    "Programming/Languages/Protobuf",
    "Programming/Languages/CSharp/Libraries/LanguageExt/LanguageExt.md",
    "Programming/Languages/CSharp/Libraries/FluentValidation.md",
    "Programming/Concepts/Design/Event Sourcing.md",
    "Programming/Languages/CSharp/Libraries/EFCore/Entities.md",
    "Programming/Languages/CSharp/Libraries/EFCore/Use SqlLite/SQLLite with EFCore.md",
    "Programming/Languages/CSharp/Tools/LinqPad/Connect To Databases/Connect Linqpad to SQLLite.md",
    "Programming/Languages/CSharp/Tools/LinqPad/Connect To Databases/ConnecToSQLLiteViaLinqPad_2.png",
    "Programming/Languages/CSharp/Tools/LinqPad/Connect To Databases/ConnecToSQLLiteViaLinqPad_1.png",
    "Programming/Languages/CSharp/Tools/LinqPad/LinqPad.md",
    "Programming/Languages/CSharp/UsefulExtension_Helpers_Patterns/Make Task canceable.md",
    "Untitled.md"
  ]
}